{
  "Emitter": {
    "Shape": "Sphere",
    "Count": 28,
    "Radius": 2.2,
    "Frequency": 0.001
  },

  "Particle": {
    "LifeTime": 0.62,

    "StartScale": 0.95,
    "EndScale": 4.6,

    "StartRotation": 0.0,
    "RotationSpeed": 18.0,

    "Velocity": [0.0, 0.0, 0.0],

    "StartColor": [1.0, 0.72, 0.2, 0.85],
    "EndColor": [0.65, 0.1, 0.0, 0.0]
  },

  "Simulation": {
    "EnableGravity": false,
    "Gravity": 0.0,

    "EnableDrag": true,
    "Drag": 0.78,

    "EnableNoise": true,
    "NoiseStrength": 3.5,

    "EnableAttraction": false,
    "AttractionStrength": 0.0
  },

  "Render": {
    "Texture": "resources/Effects/MissileExplosion/missileExplosion.png",
    "MeshType": "Board",
    "BlendMode": "Add",

    "Loop": false,
    "Duration": 0.8
  }
}
